fast_ngp/__init__.py
fast_ngp/encoding/__init__.py
fast_ngp/encoding/multi_hash_enc.py
fast_ngp/example/test.py
fast_ngp/models/__init__.py
fast_ngp/models/fast_mlp.py
fast_ngp/models/fast_nerf.py
fast_ngp/models/gigapixel_mlp.py
fast_ngp/models/nerf_mlp.py
fast_ngp/models/sdf_mlp.py
fast_ngp/rendering/__init__.py
fast_ngp/rendering/volume_render.py
fast_ngp/utils/__init__.py
fast_ngp/utils/dataset.py
fast_ngp/utils/trainer.py
fast_ngp-0.1.0.dist-info/METADATA
fast_ngp-0.1.0.dist-info/WHEEL
fast_ngp-0.1.0.dist-info/entry_points.txt
fast_ngp-0.1.0.dist-info/top_level.txt
fast_ngp-0.1.0.dist-info/RECORD
