Metadata-Version: 2.4
Name: fast-ngp
Version: 0.1.0
Summary: Pure PyTorch implementation of NVIDIA's Instant Neural Graphics Primitives
Home-page: https://github.com/Dox45/fast-ngp
Author: Your Name
Author-email: Chima Emmanuel <fender54eurois@gmail.com>
License: MIT
Project-URL: Homepage, https://github.com/Dox45/fast-ngp
Project-URL: Documentation, https://fast-ngp.readthedocs.io
Project-URL: Repository, https://github.com/Dox45/fast-ngp
Project-URL: Bug Tracker, https://github.com/Dox45/fast-ngp/issues
Keywords: nerf,neural-graphics,3d-reconstruction,pytorch,instant-ngp
Classifier: Development Status :: 3 - Alpha
Classifier: Intended Audience :: Science/Research
Classifier: License :: OSI Approved :: MIT License
Classifier: Programming Language :: Python :: 3
Classifier: Programming Language :: Python :: 3.8
Classifier: Programming Language :: Python :: 3.9
Classifier: Programming Language :: Python :: 3.10
Classifier: Programming Language :: Python :: 3.11
Requires-Python: >=3.8
Requires-Dist: torch>=2.0.0
Requires-Dist: numpy>=1.21.0
Requires-Dist: pillow>=9.0.0
Requires-Dist: tqdm>=4.62.0
Requires-Dist: matplotlib>=3.5.0
Requires-Dist: opencv-python>=4.5.0
Requires-Dist: imageio>=2.9.0
Requires-Dist: pyyaml>=6.0
Provides-Extra: dev
Requires-Dist: pytest>=7.0.0; extra == "dev"
Requires-Dist: pytest-cov>=3.0.0; extra == "dev"
Requires-Dist: black>=22.0.0; extra == "dev"
Requires-Dist: flake8>=4.0.0; extra == "dev"
Requires-Dist: isort>=5.10.0; extra == "dev"
Requires-Dist: mypy>=0.950; extra == "dev"
Provides-Extra: docs
Requires-Dist: sphinx>=4.5.0; extra == "docs"
Requires-Dist: sphinx-rtd-theme>=1.0.0; extra == "docs"
Requires-Dist: sphinx-autodoc-typehints>=1.18.0; extra == "docs"
Dynamic: author
Dynamic: home-page
Dynamic: requires-python
